{"noiseKey":{"private":{"type":"Buffer","data":"ECjBa8xweOGBQwIOIRa8Ub5reDkrz2redVpZMrmAAUM="},"public":{"type":"Buffer","data":"QVDozOAYXTKo1LqWI+hP8qDB9uzrsZspMT6xsqWdKQ8="}},"pairingEphemeralKeyPair":{"private":{"type":"Buffer","data":"oHffEK94+IyrpJPX1yZsFpG2YwfEcneL1mWY8Zrg81w="},"public":{"type":"Buffer","data":"/TYCArXou5bKrM+71AMAUfZ8+hsBEfxTg1hrN9ARkhY="}},"signedIdentityKey":{"private":{"type":"Buffer","data":"YOUHPJ6mnqwwLAClDy6KBZlazTjRT6FzXhnnGIVzp10="},"public":{"type":"Buffer","data":"e/GrPNYLZElZp6WrsKzQMUP716EQIZe0IEo1cy7tRBo="}},"signedPreKey":{"keyPair":{"private":{"type":"Buffer","data":"yOY28qEHDVK9+ytjBdyV/jWXCTjc8ly0jpwgdDgEymk="},"public":{"type":"Buffer","data":"Nlzb2WoVQLWy6N31YjGcme7jcflR4P9ODblu6kEjtgQ="}},"signature":{"type":"Buffer","data":"gLfwjgUOOk/dXSeOojlhYy2E/TzxpyYSt8Igfv4v88NWn2g7GkTywjVFk61IXJ0/bGMcySPtibTC0Ss1o3Z3iA=="},"keyId":1},"registrationId":255,"advSecretKey":"sYq6LoCq70R/zQJ0uAJk+sHxCEyT5VuBjs87mf+4hFg=","processedHistoryMessages":[{"key":{"remoteJid":"2348120659660@s.whatsapp.net","fromMe":false,"id":"3AB281EBF7CC192BB74B","participant":"","addressingMode":"pn"},"messageTimestamp":1777560290},{"key":{"remoteJid":"2348120659660@s.whatsapp.net","fromMe":false,"id":"3AD47EFECD99365353F4","participant":"","addressingMode":"pn"},"messageTimestamp":1777560290},{"key":{"remoteJid":"2348120659660@s.whatsapp.net","fromMe":false,"id":"3A6D300644BBBDBDC97F","participant":"","addressingMode":"pn"},"messageTimestamp":1777560291},{"key":{"remoteJid":"2348120659660@s.whatsapp.net","fromMe":false,"id":"3AAD433CEBCBC8684306","participant":"","addressingMode":"pn"},"messageTimestamp":1777560292},{"key":{"remoteJid":"2348120659660@s.whatsapp.net","fromMe":false,"id":"3A4B6EA187966083F38B","participant":"","addressingMode":"pn"},"messageTimestamp":1777560297}],"nextPreKeyId":813,"firstUnuploadedPreKeyId":813,"accountSyncCounter":1,"accountSettings":{"unarchiveChats":false},"registered":false,"account":{"details":"CJmWi4wOENzVzc8GGAQgACgA","accountSignatureKey":"3v6Z2MmDk2SOQIOmsRxeji6YS8sQAup8HlstZSt2VGs=","accountSignature":"HvRmm+oF+ll/G14cPbyBpL6AeXNW5DK0vQXNwIO9VaIZ1u4Hw+pJwgJH1JOGvK+mS4XGdr8csLaMNQYxjGJOgA==","deviceSignature":"94WQiJBUS46JzepPdhHQ37nDJ6E8VDVq2ert3rUsmTDSdWo51gm6g/+4SMOJ5FaG88aYnI3VgLj12VPESziWhw=="},"me":{"id":"2348120659660:33@s.whatsapp.net","lid":"97457572733148:33@lid","name":"Nexus Empire"},"signalIdentities":[{"identifier":{"name":"97457572733148:33@lid","deviceId":0},"identifierKey":{"type":"Buffer","data":"Bd7+mdjJg5NkjkCDprEcXo4umEvLEALqfB5bLWUrdlRr"}}],"platform":"iphone","routingInfo":{"type":"Buffer","data":"CAUIAggS"},"lastAccountSyncTimestamp":1777560288,"myAppStateKeyId":"AAAAAOX6"}